LICENSE.txt
MANIFEST.in
README.md
setup.cfg
setup.py
beam_mysql/__init__.py
beam_mysql/connector/__init__.py
beam_mysql/connector/client.py
beam_mysql/connector/errors.py
beam_mysql/connector/io.py
beam_mysql/connector/source.py
beam_mysql/connector/splitters.py
beam_mysql/connector/utils.py
beam_mysql_connector2.egg-info/PKG-INFO
beam_mysql_connector2.egg-info/SOURCES.txt
beam_mysql_connector2.egg-info/dependency_links.txt
beam_mysql_connector2.egg-info/requires.txt
beam_mysql_connector2.egg-info/top_level.txt