Metadata-Version: 2.4
Name: beam-mysql-connector2
Version: 1.9.0
Summary: Apache Beam I/O connector designed for accessing MySQL databases.
Home-page: https://github.com/gnomezgrave/beam-mysql-connector
Download-URL: https://pypi.python.org/pypi/beam-mysql-connector2
Author: gnomezgrave
Author-email: gnomez.grave@gmail.com
License: MIT
Keywords: Updated apache beam mysql connector based on beam-mysql-connector
Classifier: License :: OSI Approved :: MIT License
Classifier: Programming Language :: Python :: 3.8
Classifier: Programming Language :: Python :: 3.9
Classifier: Programming Language :: Python :: 3.10
Classifier: Programming Language :: Python :: 3.11
Classifier: Programming Language :: Python :: 3.12
Requires-Python: >=3.12
License-File: LICENSE.txt
Requires-Dist: apache-beam>=2.62.0
Requires-Dist: mysql-connector-python>=9.2.0
Dynamic: author
Dynamic: author-email
Dynamic: classifier
Dynamic: description
Dynamic: description-content-type
Dynamic: download-url
Dynamic: home-page
Dynamic: keywords
Dynamic: license
Dynamic: license-file
Dynamic: requires-dist
Dynamic: requires-python
Dynamic: summary
